[
  {
    "title": "2026款海豹06GT与海豹06DM-i旅行版4月2日正式上市：闪充成标配，激光雷达可选",
    "url": "http://auto.cnfol.com/cheshidongtai/20260402/32121906.shtml",
    "publish_date": "2026-04-02",
    "keyword": "新车发布",
    "desc": "比亚迪海洋网推出2026款海豹06GT与海豹06DM-i旅行版，前者搭载第二代刀片电池与闪充技术，纯电续航620公里，电机最大功率240kW，百公里加速6.5秒，可选装激光雷达。海豹06DM-i旅行版为比亚迪首款纯电续航达300公里的插混车型，全系标配云辇-C智能底盘系统。",
    "image": "http://mpimg.cnfol.com/cover/202604/02/7f11e7deb8ae9e792fca73235c866e4b.png"
  },
  {
    "title": "比亚迪4月10日举办智能驾驶发布会：璇玑ASIC芯片亮相，激光雷达下探至6万级车型",
    "url": "https://baijiahao.baidu.com/s?id=1860754105130331601",
    "publish_date": "2026-03-31",
    "keyword": "智能驾驶",
    "desc": "比亚迪将于4月10日举办高规格智能驾驶技术发布会，核心亮点为全栈自研璇玑ASIC智驾芯片，实现一芯多域架构，成本仅为外购芯片1/3。同时计划将激光雷达成本压至千元级，下放至10万级乃至6万级海鸥等入门车型，开启全民智驾时代。",
    "image": ""
  },
  {
    "title": "北京率先启动智能网联新能源汽车专属商业保险，统一适配L2至L4全级别",
    "url": "https://www.donews.com/news/detail/8/6488463.html",
    "publish_date": "2026-03-29",
    "keyword": "智能驾驶",
    "desc": "北京金融监管局宣布在全国率先启动智能网联新能源汽车商业保险产品开发应用，可统一适配L2至L4全级别智能网联新能源汽车。新产品创新引入先行赔付+事后追偿机制，覆盖人机共驾与自动驾驶场景下的责任认定及软硬件升级损失等新风险。",
    "image": "https://img6.donews.com/img/2023/03/08/img_pic_571678243954.png"
  },
  {
    "title": "智能网联汽车两项系列团体标准正式发布，聚焦协同式驾驶与复杂道路自动驾驶",
    "url": "https://finance.sina.cn/2026-03-30/detail-inhsueew9713272.d.html",
    "publish_date": "2026-03-30",
    "keyword": "智能驾驶",
    "desc": "3月28日，中国自动化学会在2026国家新质生产力与智能产业发展会议上，发布《基于先进移动通信的协同式智能网联汽车》和《复杂道路自动驾驶》两个系列标准，聚焦协同式驾驶与复杂道路场景挑战，为自动驾驶安全落地提供可靠遵循。",
    "image": "https://n.sinaimg.cn/spider20260330/511/w1267h844/20260330/8455-d6b7cbe94acc467b3d7f7a8e72485591.jpg"
  },
  {
    "title": "全新奥迪A6L正式上市32.29万起，首搭华为乾崑智驾+双激光雷达",
    "url": "https://news.m.yiche.com/hao/wenzhang/108705462/",
    "publish_date": "2026-03-30",
    "keyword": "新车发布",
    "desc": "3月25日，一汽奥迪全新奥迪A6L正式上市，指导价32.29万至43.59万元，推出四款配置。全新A6L基于奥迪PPC平台打造，搭载深度定制的华为乾崑智驾技术，配备双激光雷达，支持城区NOA、高速NOA及跨层记忆泊车等全场景智驾功能，同步开启A6L e-tron预售。",
    "image": ""
  },
  {
    "title": "4月1日充电新政落地：小区装桩全面提速，补能痛点精准击破",
    "url": "https://k.sina.cn/article_5633622886_14fca4366027012uvi.html",
    "publish_date": "2026-03-30",
    "keyword": "充电技术",
    "desc": "2026年4月1日，全国新能源汽车充电基础设施新政正式落地，覆盖充电桩建设、私人装桩、收费监管、运维服务全链条，物业不得无故阻挠装桩申请，租赁车位只要有一年以上使用权均可办理，电动车补能配套全面升级。",
    "image": ""
  },
  {
    "title": "2026款比亚迪海豹06GT提前曝光：搭载第二代刀片电池，4月2日定档上市",
    "url": "https://new.qq.com/rain/a/20260327A04X3H00",
    "publish_date": "2026-03-27",
    "keyword": "电池技术",
    "desc": "比亚迪2026款海豹06GT与海豹06DM-i旅行版定于4月2日上市。海豹06GT搭载第二代刀片电池与极速闪充，常温下10%-70%充电仅需5分钟，零下30度极寒环境充电时间仅比常温多3分钟，同时引入云辇-C智能底盘路面预瞄功能，运动性能与补能效率大幅提升。",
    "image": ""
  }
]